Metadata-Version: 2.1
Name: fkcenters
Version: 1.0.3
Summary: A python package for Fuzzy-k-Centers algorithm
Home-page: https://github.com/nmtoan91/fkcenters
Author: nmtoan91
Author-email: toan_stt@yahoo.com
License: UNKNOWN
Platform: UNKNOWN
Classifier: Programming Language :: Python :: 3
Classifier: License :: OSI Approved :: MIT License
Classifier: Operating System :: OS Independent
Requires-Python: >=3.6
